tmux_list_learner/__init__.py
tmux_list_learner/config.py
tmux_list_learner/tmux_list_learner.py
tmux_list_learner/scripts/__init__.py
tmux_list_learner/scripts/tmux_list_learner.py
tmux_list_learner-0.2.0.dist-info/LICENSE.md
tmux_list_learner-0.2.0.dist-info/METADATA
tmux_list_learner-0.2.0.dist-info/WHEEL
tmux_list_learner-0.2.0.dist-info/entry_points.txt
tmux_list_learner-0.2.0.dist-info/top_level.txt
tmux_list_learner-0.2.0.dist-info/RECORD
