Metadata-Version: 2.1
Name: tmux-list-learner
Version: 0.2.0
Summary: List learning tool using tmux windows
Home-page: https://github.com/flaxandteal/tmux_list_learner
Author: Phil Weir
Author-email: phil.weir@flaxandteal.co.uk
License: MIT
Keywords: tmux learning
Platform: UNKNOWN
Classifier: Development Status :: 4 - Beta
Classifier: Intended Audience :: Developers
Classifier: License :: OSI Approved :: MIT License
Classifier: Programming Language :: Python :: 3.7
Requires-Dist: Click
Requires-Dist: appdirs
Requires-Dist: pyyaml
